groupstackbar/__init__.py
groupstackbar-0.0.3.dist-info/LICENSE
groupstackbar-0.0.3.dist-info/METADATA
groupstackbar-0.0.3.dist-info/WHEEL
groupstackbar-0.0.3.dist-info/top_level.txt
groupstackbar-0.0.3.dist-info/RECORD
