Metadata-Version: 2.1
Name: groupstackbar
Version: 0.0.3
Summary: groupstackbar package
Home-page: UNKNOWN
Author: Nishant Kumar
Author-email: abc.nishant007@gmail.com
License: UNKNOWN
Platform: UNKNOWN
Classifier: Programming Language :: Python :: 3
Classifier: License :: OSI Approved :: MIT License
Classifier: Operating System :: OS Independent
Requires-Python: >=3.6
